{
    "sourceFile": "layout/context/apiClient.js",
    "activeCommit": 0,
    "commits": [
        {
            "activePatchIndex": 0,
            "patches": [
                {
                    "date": 1736741923735,
                    "content": "Index: \n===================================================================\n--- \n+++ \n"
                }
            ],
            "date": 1736741923735,
            "name": "Commit-0",
            "content": "import axios from 'axios';\r\nimport Cookies from 'js-cookie';\r\n\r\nconst apiClient = axios.create({\r\n  baseURL: 'http://192.168.14.248:2356/api/v1/logout',\r\n});\r\n\r\nexport default apiClient;"
        }
    ]
}